<?xml version="1.0" encoding="UTF-8"?>

<openerp>
    <data noupdate="0">

        <record id="apt_group_a1" model="apt.group">
            <field name="name">A1</field>
        </record>

        <record id="apt_group_a2" model="apt.group">
            <field name="name">A2</field>
        </record>

        <record id="apt_group_b" model="apt.group">
            <field name="name">B</field>
        </record>

        <record id="apt_group_c1" model="apt.group">
            <field name="name">C1</field>
        </record>

        <record id="apt_group_c2" model="apt.group">
            <field name="name">C2</field>
        </record>

        <record id="apt_group_d" model="apt.group">
            <field name="name">D</field>
        </record>

        <record id="apt_group_e" model="apt.group">
            <field name="name">E</field>
        </record>

    </data>
</openerp>
